CHANGELOG.rst
COPYING
MANIFEST.in
README.rst
TODO.rst
setup.py
bin/kolekto
kolekto/__init__.py
kolekto/config.py
kolekto/db.py
kolekto/exceptions.py
kolekto/helpers.py
kolekto/movie.py
kolekto/printer.py
kolekto/tmdb_proxy.py
kolekto.egg-info/PKG-INFO
kolekto.egg-info/SOURCES.txt
kolekto.egg-info/dependency_links.txt
kolekto.egg-info/entry_points.txt
kolekto.egg-info/requires.txt
kolekto.egg-info/top_level.txt
kolekto.egg-info/zip-safe
kolekto/commands/__init__.py
kolekto/commands/config.py
kolekto/commands/dump.py
kolekto/commands/edit.py
kolekto/commands/find_duplicates.py
kolekto/commands/flags.py
kolekto/commands/gc.py
kolekto/commands/importer.py
kolekto/commands/init.py
kolekto/commands/link.py
kolekto/commands/list.py
kolekto/commands/refresh.py
kolekto/commands/restore.py
kolekto/commands/rm.py
kolekto/commands/show.py
kolekto/commands/stats.py
kolekto/datasources/__init__.py
kolekto/datasources/mediainfos.py
kolekto/datasources/tmdb.py
kolekto/profiles/__init__.py
kolekto/profiles/movies.py