Metadata-Version: 1.1
Name: kolekto
Version: 1.2
Summary: A really KISS movie catalog software
Home-page: https://github.com/NaPs/Kolekto
Author: Antoine Millet
Author-email: antoine@inaps.org
License: MIT
Keywords: kolekto movies
Platform: UNKNOWN
Classifier: Development Status :: 4 - Beta
Classifier: License :: OSI Approved :: MIT License
Classifier: Operating System :: OS Independent
